LICENSE.txt
MANIFEST.in
README.rst
setup.py
docs/Makefile
docs/api.rst
docs/changelog.rst
docs/conf.py
docs/index.rst
docs/installation.rst
docs/quick_start.rst
docs/_static/README
purestorage/__init__.py
purestorage/purestorage.py
purestorage.egg-info/PKG-INFO
purestorage.egg-info/SOURCES.txt
purestorage.egg-info/dependency_links.txt
purestorage.egg-info/requires.txt
purestorage.egg-info/top_level.txt