Metadata-Version: 1.1
Name: purestorage
Version: 1.16.0
Summary: Pure Storage FlashArray REST Client
Home-page: https://github.com/purestorage/rest-client
Author: Pure Storage
Author-email: wes@purestorage.com
License: BSD 2-Clause
Download-URL: https://github.com/purestorage/rest-client/archive/1.16.0.tar.gz
Keywords: pure,storage,flasharray,rest,client
Platform: UNKNOWN
